setup.py
transmon/__init__.py
transmon/analyzer.py
transmon/fetcher.py
transmon/project.py
transmon.egg-info/PKG-INFO
transmon.egg-info/SOURCES.txt
transmon.egg-info/dependency_links.txt
transmon.egg-info/entry_points.txt
transmon.egg-info/requires.txt
transmon.egg-info/top_level.txt