Metadata-Version: 1.2
Name: transmon
Version: 0.1
Summary: Translation monitor
Home-page: https://framagit.org/tyreunom/transmon
Author: Julien Lepiller
Author-email: julien@lepiller.eu
License: AGPLv3+
Keywords: translation monitor
Platform: UNKNOWN
Classifier: Development Status :: 3 - Alpha
Classifier: Intended Audience :: Developers
Classifier: Topic :: Software Development :: Localization
Classifier: License :: OSI Approved :: GNU Affero General Public License v3 or later (AGPLv3+)
Classifier: Programming Language :: Python :: 3
Requires-Python: >=3
